tagit/__init__.py
tagit/configs.py
tagit/dtaglist.py
tagit/exp.py
tagit/experiment.py
tagit/locker.py
tagit/main.py
tagit/parser.py
tagit/query.py
tagit/taglist.py
tagit/utils.py
etagit-0.0.11.dist-info/LICENSE
etagit-0.0.11.dist-info/METADATA
etagit-0.0.11.dist-info/WHEEL
etagit-0.0.11.dist-info/entry_points.txt
etagit-0.0.11.dist-info/top_level.txt
etagit-0.0.11.dist-info/RECORD
