Metadata-Version: 2.1
Name: etagit
Version: 0.0.11
Summary: CLI tagging system for experiments
Home-page: https://github.com/yunjae2/tagit
Author: Yunjae Lee
Author-email: lyj7694@gmail.com
License: UNKNOWN
Platform: UNKNOWN
Classifier: Programming Language :: Python :: 3
Classifier: License :: OSI Approved :: MIT License
Classifier: Operating System :: OS Independent
Requires-Python: >=3.6
